setup.py
bin/tf
pytf/__init__.py
pytf/argparser.py
pytf/pytf.py
pytf/util.py
pytf.egg-info/PKG-INFO
pytf.egg-info/SOURCES.txt
pytf.egg-info/dependency_links.txt
pytf.egg-info/not-zip-safe
pytf.egg-info/requires.txt
pytf.egg-info/top_level.txt