Metadata-Version: 1.0
Name: pytf
Version: 0.2
Summary: 2lemetry ThingFabric Command Line Interface
Home-page: http://github.com/benkershner/tf-cli
Author: Ben Kershner
Author-email: ben.kershner@gmail.com
License: MIT
Platform: UNKNOWN
